trackbranch/__init__.py
trackbranch/main.py
trackbranch-0.1.5.dist-info/entry_points.txt
trackbranch-0.1.5.dist-info/LICENSE
trackbranch-0.1.5.dist-info/WHEEL
trackbranch-0.1.5.dist-info/METADATA
trackbranch-0.1.5.dist-info/RECORD
