Metadata-Version: 2.1
Name: trackbranch
Version: 0.1.5
Summary: Maintain branch collection profiles for Git repositories
Home-page: https://github.com/kevr/trackbranch
License: MIT
Keywords: git,branch,profiles
Author: Kevin Morris
Author-email: kevr@0cost.org
Maintainer: Kevin Morris
Maintainer-email: kevr@0cost.org
Requires-Python: >=3.6,<4.0
Classifier: License :: OSI Approved :: MIT License
Classifier: Programming Language :: Python :: 3
Classifier: Programming Language :: Python :: 3.10
Classifier: Programming Language :: Python :: 3.6
Classifier: Programming Language :: Python :: 3.7
Classifier: Programming Language :: Python :: 3.8
Classifier: Programming Language :: Python :: 3.9
Project-URL: Repository, https://github.com/kevr/trackbranch
